aiaas_falcon.py
aiaas_falcon-0.2.2.dist-info/METADATA
aiaas_falcon-0.2.2.dist-info/WHEEL
aiaas_falcon-0.2.2.dist-info/RECORD
