Metadata-Version: 2.1
Name: aiaas-falcon
Version: 0.2.2
Summary: This python package help to interact with Generative AI - Large Language Models. It interacts with AIaaS LLM , AIaaS embedding , AIaaS Audio set of APIs to cater the request.
License: MIT
Author: Your Name
Author-email: you@example.com
Requires-Python: >=3.8.1,<4.0.0
Classifier: License :: OSI Approved :: MIT License
Classifier: Programming Language :: Python :: 3
Classifier: Programming Language :: Python :: 3.9
Classifier: Programming Language :: Python :: 3.10
Classifier: Programming Language :: Python :: 3.11
Requires-Dist: black (>=23.9.1,<24.0.0)
Requires-Dist: flake8 (>=6.1.0,<7.0.0)
Requires-Dist: google-api-core (>=2.12.0,<3.0.0)
Requires-Dist: interrogate (>=1.5.0,<2.0.0)
Requires-Dist: isort (>=5.12.0,<6.0.0)
Requires-Dist: pandas (>=1.0.0,<2.1.4)
Requires-Dist: pytest (>=7.4.2,<8.0.0)
Requires-Dist: requests (>=2.31.0,<3.0.0)
